tests/__init__.py
tests/test_config.py
tests/test_threatfox.py
threatfox/__init__.py
threatfox/cli.py
threatfox/config.py
threatfox-1.0.0.dist-info/LICENSE
threatfox-1.0.0.dist-info/METADATA
threatfox-1.0.0.dist-info/WHEEL
threatfox-1.0.0.dist-info/entry_points.txt
threatfox-1.0.0.dist-info/top_level.txt
threatfox-1.0.0.dist-info/RECORD
