Metadata-Version: 2.1
Name: threatfox
Version: 1.0.0
Summary: Python library and command line tool for interacting with the ThreatFox API provided by abuse.ch.
Home-page: https://github.com/seanmcfeely/ThreatFox
Author: Sean McFeely
Author-email: mcfeelynaes@gmail.com
License: UNKNOWN
Project-URL: Bug Tracker, https://github.com/seanmcfeely/ThreatFox/issues
Keywords: Threat Fox,ThreatFox,abuse.ch,Threat Intel
Platform: UNKNOWN
Classifier: Development Status :: 3 - Alpha
Classifier: Intended Audience :: Developers
Classifier: Intended Audience :: Information Technology
Classifier: Programming Language :: Python :: 3
Classifier: License :: OSI Approved :: MIT License
Classifier: Operating System :: OS Independent
Requires-Python: >=3.7
License-File: LICENSE
Requires-Dist: argparse
Requires-Dist: coloredlogs
Requires-Dist: aiodns
Requires-Dist: aiohttp
